{
  "selected_article": {
    "original_title": "구글의 내부용 '에이전트 스미스' 인기 폭발...\"접근 제한할 정도\"",
    "link": "https://www.aitimes.com/news/articleView.html?idxno=208499",
    "reason": "구글 내부에서만 쓰는 비밀 AI 도구가 너무 인기가 많아서 접근을 제한해야 할 정도라는 것은 개발자들이 매우 흥미로워할 만한 소식이고, '에이전트 스미스'라는 매트릭스 악역 이름도 화제성이 있음. 또한 구글 내부 도구가 얼마나 강력한지에 대한 궁금증을 자극해 댓글 유발 가능성이 높음"
  },
  "post_main": "구글이 사내에서만 쓰는 '에이전트 스미스'라는 AI 코딩 도구가 있는데, 인기가 너무 폭발적이라 직원들의 접근을 제한해야 할 정도래요 🤔\n\n매트릭스 악역 이름을 딴 이 도구는 올해 초에 개발됐고, 코딩 작업을 자동화해주는데 구글 내부 시스템과 연동도 된다고 합니다. 그런데 너무 많은 직원들이 몰려들어서 사용량을 통제해야 할 상황이 됐다는 거죠.\n\n솔직히 구글 개발자들도 줄 서서 쓰고 싶어하는 AI 도구면... 얼마나 좋길래 그럴까요? 너희는 이런 강력한 내부 도구, 부럽다고 생각해 아니면 뭔가 무섭다고 생각해?",
  "reply_explain": "쉽게 말하면 구글이 자기네 개발자들 업무용으로 만든 AI 코딩 도구가 있는데, 성능이 워낙 좋다보니 사내에서 쓰려는 사람이 너무 많아져서 \"대기줄 서세요\" 상태가 된 거임",
  "reply_important": "이게 왜 중요하냐면 구글 수준의 개발자들도 감탄할 만큼 좋은 AI 도구라는 뜻이거든요. 보통 빅테크 내부 도구들이 나중에 외부 제품으로 나오는 경우가 많으니, 우리가 곧 쓸 수 있는 도구의 미리보기일 수도 있고요",
  "reply_action": "지금 당장은 구글 내부용이라 못 써보지만, 비슷한 오픈소스 코딩 에이전트들 써보는 게 좋을듯. 아니면 구글이 언제 이거 공개할지 지켜보거나. 분명 곧 비슷한 기능들이 시장에 나올 거예요",
  "reply_counter": "근데 반대로 보면 이게 너무 강력해서 구글이 의도적으로 내부에만 두고 있는 걸 수도 있어요. 외부 공개했다가 코딩 시장이 너무 급격히 바뀌는 걸 우려하는 건 아닐까요?",
  "reply_casual": "ㄹㅇ 매트릭스 악역 이름을 붙인 센스는 인정 ㅋㅋ 근데 진짜 궁금한 건 이거 언제 우리도 써볼 수 있을까 하는 거임",
  "topic_tag": "AI 뉴스",
  "og_image": "https://cdn.aitimes.com/news/photo/202603/208499_210786_2520.png",
  "source_link": "https://www.aitimes.com/news/articleView.html?idxno=208499"
}