{
  "selected_article": {
    "original_title": "아마존, AI 에이전트 자기 개선을 위한 범용 인프라 'A-이볼브' 발표",
    "link": "https://www.aitimes.com/news/articleView.html?idxno=208524",
    "reason": "AI가 스스로 코드를 개선하는 자가진화 시스템은 개발자 일자리에 직접적인 위협이 되는 동시에, 인간의 개입 없이 AI가 자가발전한다는 점에서 SF적 공포감을 자극할 수 있음"
  },
  "post_main": "아마존이 AI가 스스로 자기 코드를 개선하는 'A-이볼브' 시스템을 공개했다고 하네 🤔\n\n이전엔 AI 에이전트가 실패하면 개발자가 직접 분석하고 코드 수정해야 했는데, 이젠 AI가 알아서 자기 문제점 찾아서 스스로 업그레이드한다는 거임. 인간 개입 없이 자가진화하는 시스템이라니...\n\n솔직히 개발자들 입장에선 이거 좋은 뉴스야 나쁜 뉴스야?",
  "reply_explain": "쉽게 말하면 지금까진 AI가 고장나면 사람이 고쳐줘야 했는데, 이젠 AI가 스스로 자기 문제 찾아서 고친다는 얘기. 마치 로봇이 자기 부품을 스스로 교체하는 것처럼.",
  "reply_important": "이게 왜 중요하냐면 개발자의 핵심 업무 중 하나인 '디버깅과 최적화'가 자동화된다는 뜻. 아마존이 이걸 범용 인프라로 공개했다는 건 업계 전체가 이 방향으로 갈 거란 신호임.",
  "reply_action": "지금 당장 AI 도구 사용법 익히고, 단순 반복 작업보다는 창의적 설계나 전략적 사고가 필요한 업무로 포지션 바꿔야 할듯. 자동화 못하는 영역으로 피해야 함.",
  "reply_counter": "근데 반대로 보면 개발자가 더 고차원 작업에 집중할 수 있게 해주는 도구일 수도 있음. 삽질하는 시간 줄이고 진짜 중요한 아키텍처 설계에 몰두할 기회가 될 수도?",
  "reply_casual": "ㄹㅇ 이러다 3년 뒤엔 AI가 AI 만드는 시대 올듯ㅋㅋ 인간은 뭘 해야 하나",
  "topic_tag": "ai.threads",
  "og_image": "https://cdn.aitimes.com/news/photo/202603/208524_210825_2851.png",
  "source_link": "https://www.aitimes.com/news/articleView.html?idxno=208524"
}